{"_st_flags_present_": ["bin/cpdup/cpdup.c", "bin/cpdup/hcproto.c", "bin/sh/eval.c", "bin/sh/parser.c", "bin/sh/expand.c", "lib/libc/resolv/res_send.c", "lib/libc/net/name6.c", "lib/libc/net/getaddrinfo.c", "lib/libc/locale/utf8.c", "lib/libc/gen/getpwent.c", "lib/libc/stdio/vfwprintf.c", "lib/libc/stdio/vfprintf.c", "lib/libc/stdlib/nmalloc.c", "lib/libc/stdtime/localtime.c", "lib/libdm/dm_task.c", "lib/librefuse/refuse.c", "lib/libalias/alias_db.c", "lib/libtacplus/taclib.c", "lib/libfetch/http.c", "lib/libdmsg/msg.c", "lib/libdmsg/msg_lnk.c", "lib/libtcplay/tcplay.c", "lib/libc_r/test/mutex_d.c", "lib/libevtr/evtr.c", "lib/libevtr/ktrfmt.yy.c", "lib/libevtr/ktrfmt.tab.c", "lib/libpuffs/puffs.h", "lib/libc_r/uthread/pthread_private.h"], "_st_fsmid_present_": ["bin/cpdup/cpdup.c", "bin/cpdup/hcproto.c", "bin/sh/parser.c", "bin/sh/expand.c", "bin/ls/ls.c", "lib/libc/resolv/res_send.c", "lib/libc/net/getaddrinfo.c", "lib/libc/gen/getpwent.c", "lib/libc/stdtime/localtime.c", "lib/libalias/alias_db.c", "lib/libtacplus/taclib.c", "lib/libdmsg/msg.c", "lib/libdmsg/msg_lnk.c", "lib/libevtr/evtr.c", "lib/libevtr/ktrfmt.yy.c", "lib/libevtr/ktrfmt.tab.c", "lib/libpuffs/puffs.h"], "debug_malloc": ["bin/cpdup/misc.c", "bin/cpdup/cpdup.h"], "fts_whiteout": ["bin/ls/ls.c", "bin/rm/rm.c", "lib/libc/gen/fts.c"], "use_poll": ["lib/libc/resolv/res_send.c", "lib/libc/isc/eventlib_p.h"], "have_stropts_h": ["lib/libarchive/config.h", "lib/libssh/config.h"], "have_sa_len": ["lib/libc/resolv/res_send.c", "lib/libc/net/ip6opt.c", "lib/libc/nameser/ns_print.c", "lib/libfetch/http.c", "lib/libipsec/pfkey.c", "lib/libdmsg/msg.c", "lib/libradius/radlib.c", "lib/libc/include/port_after.h", "lib/libarchive/config.h", "lib/libssh/config.h"], "res_use_edns0": ["lib/libc/resolv/res_send.c", "lib/libc/resolv/res_query.c", "lib/libc/resolv/res_init.c", "lib/libc/net/getaddrinfo.c", "lib/librefuse/refuse.c"], "has_inet6_structs": ["lib/libc/include/port_after.h"], "ns_caching": ["lib/libc/net/nsdispatch.c", "lib/libc/net/getservent.c", "lib/libc/gen/getgrent.c", "lib/libc/gen/getpwent.c"], "yp": ["lib/libc/yp/yplib.c", "lib/libc/locale/table.c", "lib/libtelnet/encrypt.c"], "locale_debug": ["lib/libc/locale/lmonetary.c", "lib/libc/locale/lmessages.c", "lib/libc/locale/lnumeric.c"], "ldbl_implicit_nbit": ["lib/libc/gdtoa/_hldtoa.c", "lib/libc/gdtoa/_ldtoa.c", "lib/libc/x86_64/_fpmath.h"], "__x86_64__": ["lib/libcrypt/crypt-sha512.c", "lib/libdmsg/icrc.c"], "no_floating_point": ["lib/libc/stdio/vfwprintf.c", "lib/libc/stdio/printf-pos.c", "lib/libc/stdio/vfprintf.c", "lib/libc/stdio/vfwscanf.c", "lib/libc/stdio/vfscanf.c", "lib/libc/stdio/printfcommon.h"], "sysv_rwlock": ["lib/libc/sysvipc/msg.c", "lib/libc/sysvipc/shm.c", "lib/libc/sysvipc/sem.c", "lib/libc/sysvipc/ipc.c", "lib/libc/sysvipc/lock.c", "lib/libc/sysvipc/sysvipc_msg.h", "lib/libc/sysvipc/sysvipc_sem.h", "lib/libc/sysvipc/sysvipc_lock.h"], "sysv_sems": ["lib/libc/gen/sysvipc_semget.c", "lib/libc/sysvipc/shm.c", "lib/libc/sysvipc/sem.c", "lib/libc/sysvipc/ipc.c", "lib/libc/sysvipc/sysvipc_shm.h", "lib/libc/sysvipc/sysvipc_ipc.h", "lib/libc/sysvipc/sysvipc_sem.h"], "rpc_debug": ["lib/libstand/rpc.c"], "mem_chk": ["bin/pax/tar.c", "bin/sh/parser.c", "lib/libc/db/test/dbtest.c"], "tm_zone": ["lib/libc/stdlib/dmalloc.c", "lib/libc/stdlib/nmalloc.c", "lib/libc/stdtime/localtime.c", "lib/libc/stdtime/strftime.c", "lib/libc/stdtime/strptime.c", "lib/libc/stdtime/private.h", "lib/libmagic/config.h"], "tm_gmtoff": ["lib/libc/stdtime/localtime.c", "lib/libc/stdtime/strftime.c", "lib/libftpio/ftpio.c", "lib/libc/stdtime/private.h", "lib/libmagic/config.h", "lib/libarchive/config.h"], "ipv6_portrange": ["lib/libc/rpc/bindresvport.c", "lib/libftpio/ftpio.c", "lib/libfetch/ftp.c"], "no_fw_punch": ["lib/libalias/alias_db.c", "lib/libalias/alias.h"], "support_dhcp": ["lib/libstand/bootp.c"], "krb4_encpwd": ["lib/libtelnet/auth.c", "lib/libtelnet/krb4encpwd.c"], "rsa_encpwd": ["lib/libtelnet/auth.c", "lib/libtelnet/read_password.c", "lib/libtelnet/rsaencpwd.c"], "ni_withscopeid": ["lib/libutil/logwtmp.c"], "debug_thread_kern": ["lib/libthread_db/libthread_xu.c", "lib/libthread_xu/thread/thr_kern.c", "lib/libthread_xu/thread/thr_list.c", "lib/libusb/libusb10.c", "lib/libc_r/test/mutex_d.c", "lib/libc_r/uthread/uthread_gc.c", "lib/libc_r/uthread/uthread_priority_queue.c", "lib/libc_r/uthread/uthread_fd.c", "lib/libc_r/uthread/uthread_mutex.c", "lib/libc_r/uthread/uthread_create.c", "lib/libc_r/uthread/uthread_init.c", "lib/libc_r/uthread/uthread_cond.c", "lib/libc_r/uthread/uthread_sig.c", "lib/libc_r/uthread/uthread_kern.c", "lib/libthread_xu/thread/thr_private.h", "lib/libc_r/uthread/pthread_private.h"], "debug_signal": ["lib/libthread_xu/thread/thr_sig.c", "lib/libc_r/uthread/uthread_sig.c"], "libusb_global_include_file": ["lib/libusb/libusb20.c", "lib/libusb/libusb10_desc.c", "lib/libusb/libusb01.c", "lib/libusb/libusb20_desc.c", "lib/libusb/libusb10_hotplug.c", "lib/libusb/libusb20_ugen20.c", "lib/libusb/libusb10_io.c", "lib/libusb/libusb10.c", "lib/libusb/libusb20_int.h", "lib/libusb/libusb_global_linux.h", "lib/libusb/libusb.h", "lib/libusb/libusb20.h", "lib/libusb/libusb20_desc.h"], "yy__ktrfmt_ktrfmt_tab_h_included": ["lib/libevtr/ktrfmt.yy.c", "lib/libevtr/ktrfmt.tab.c", "lib/libevtr/ktrfmt.tab.h"], "yyparse_param": ["lib/libevtr/ktrfmt.tab.c", "lib/libevtr/ktrfmt.tab.h"], "_pax_": ["bin/pax/pax.h"], "_lock_debug": ["lib/libc_r/uthread/uthread_fd.c", "lib/libc_r/uthread/pthread_private.h"], "_posix_pthread_semantics": ["lib/libc/gen/sysconf.c", "lib/libc_r/test/mutex_d.c", "lib/libc_r/uthread/uthread_mutex.c", "lib/libc_r/uthread/uthread_sig.c", "bin/csh/config_p.h", "lib/liblzma/config.h", "lib/libmagic/config.h", "lib/libpam/libpam/config.h", "lib/libarchive/config.h", "lib/libedit/libedit/config.h", "lib/libldns/ldns/config.h"], "__extensions__": ["lib/libpam/libpam/config.h", "lib/libedit/libedit/config.h"], "words_bigendian": ["lib/liblzma/config.h", "lib/libmagic/config.h", "lib/libexpat/expat_config.h", "lib/libldns/ldns/config.h"], "_darwin_use_64_bit_inode": ["bin/df/df.c", "bin/pax/tables.c", "bin/pax/pax.c", "bin/ls/ls.c", "bin/ls/print.c", "lib/librefuse/refuse.c", "lib/i18n_module/UTF7/citrus_utf7.c", "lib/libcrypt/crypt-sha512.c", "lib/libcrypt/crypt-des.c", "lib/libhammer/stats.c", "lib/libstand/ext2fs.c", "lib/libstand/hammer2.c", "lib/libstand/hammer1.c", "lib/libtelnet/enc_des.c", "lib/libdmsg/icrc.c", "bin/pax/tables.h", "lib/liblzma/config.h", "lib/libmagic/config.h", "lib/libarchive/config.h", "lib/libhammer/libhammer.h", "lib/libssh/config.h"], "_netgraph_h_": ["lib/libnetgraph7/netgraph.h", "lib/libnetgraph/netgraph.h"]}